README.md
setup.cfg
setup.py
src/ExpdFtpService/__init__.py
src/ExpdFtpService.egg-info/PKG-INFO
src/ExpdFtpService.egg-info/SOURCES.txt
src/ExpdFtpService.egg-info/dependency_links.txt
src/ExpdFtpService.egg-info/requires.txt
src/ExpdFtpService.egg-info/top_level.txt