Metadata-Version: 1.0
Name: ExpdFtpService
Version: 0.4.0
Summary: Python Module for download / upload file on Expeditors Ftp Server
Home-page: UNKNOWN
Author: greg he
Author-email: greg.he@expeditors.com
License: MIT
Keywords: download / upload ftp file
Platform: UNKNOWN
